starui/__init__.py
starui/cli/__init__.py
starui/cli/add.py
starui/cli/build.py
starui/cli/dev.py
starui/cli/init.py
starui/cli/list.py
starui/cli/main.py
starui/cli/utils.py
starui/config.py
starui/css/__init__.py
starui/css/binary.py
starui/css/builder.py
starui/dev/__init__.py
starui/dev/analyzer.py
starui/dev/process_manager.py
starui/dev/unified_reload.py
starui/registry/__init__.py
starui/registry/client.py
starui/registry/component_metadata.py
starui/registry/components/__init__.py
starui/registry/components/accordion.py
starui/registry/components/alert.py
starui/registry/components/alert_dialog.py
starui/registry/components/avatar.py
starui/registry/components/badge.py
starui/registry/components/breadcrumb.py
starui/registry/components/button.py
starui/registry/components/card.py
starui/registry/components/checkbox.py
starui/registry/components/code_block.py
starui/registry/components/dialog.py
starui/registry/components/hover_card.py
starui/registry/components/input.py
starui/registry/components/label.py
starui/registry/components/popover.py
starui/registry/components/progress.py
starui/registry/components/radio_group.py
starui/registry/components/select.py
starui/registry/components/separator.py
starui/registry/components/sheet.py
starui/registry/components/switch.py
starui/registry/components/tabs.py
starui/registry/components/textarea.py
starui/registry/components/theme_toggle.py
starui/registry/components/toggle.py
starui/registry/components/toggle_group.py
starui/registry/components/typography.py
starui/registry/components/utils.py
starui/registry/dependencies.py
starui/registry/loader.py
starui/registry/local.py
starui/templates/__init__.py
starui/templates/app_starter.py
starui/templates/css_input.py
starui-0.1.8.dist-info/WHEEL
starui-0.1.8.dist-info/entry_points.txt
starui-0.1.8.dist-info/METADATA
starui-0.1.8.dist-info/RECORD
