Metadata-Version: 2.3
Name: starui
Version: 0.1.8
Summary: Python-first UI component library for Datastar/StarHTML applications
Keywords: ui,components,tailwind,datastar,starhtml,fasthtml
Author: firefly
Classifier: Development Status :: 3 - Alpha
Classifier: Intended Audience :: Developers
Classifier: Topic :: Software Development :: Libraries :: Python Modules
Classifier: Topic :: Software Development :: User Interfaces
Classifier: Programming Language :: Python :: 3
Classifier: Programming Language :: Python :: 3.12
Requires-Dist: typer>=0.9.0,<1.0.0
Requires-Dist: requests>=2.31.0,<3.0.0
Requires-Dist: pydantic>=2.5.0,<3.0.0
Requires-Dist: rich>=13.7.0,<14.0.0
Requires-Dist: starhtml==0.1.13
Requires-Dist: websockets>=12.0.0,<13.0.0
Requires-Python: >=3.12
